statement_parser/Bank.py
statement_parser/Transaction.py
statement_parser/__init__.py
statement_parser/banks/HdfcCredit.py
statement_parser/banks/HsbcCredit.py
statement_parser/banks/HsbcDebit.py
statement_parser/banks/IciciCredit.py
statement_parser/banks/IciciDebit.py
statement_parser/banks/KotakDebit.py
statement_parser/banks/Wallet.py
statement_parser-0.0.12.dist-info/licenses/LICENSE
statement_parser-0.0.12.dist-info/METADATA
statement_parser-0.0.12.dist-info/WHEEL
statement_parser-0.0.12.dist-info/top_level.txt
statement_parser-0.0.12.dist-info/RECORD
