Metadata-Version: 2.4
Name: statement_parser
Version: 0.0.12
Summary: Bank Statement Parser is a Python library designed to parse and normalize transaction data from various bank statement formats ( CSV, Excel, etc.) into a consistent and easy-to-use Pandas DataFrame. It supports multiple banks and file formats, making it a versatile tool for financial data analysis.
Author-email: Khuzema Challawala <khuzema.ac@gmail.com>
Classifier: Programming Language :: Python :: 3
Classifier: License :: OSI Approved :: GNU General Public License (GPL)
Classifier: Operating System :: OS Independent
Requires-Python: >=3.7
License-File: LICENSE
Requires-Dist: pandas>=2.2.3
Requires-Dist: numpy>=2.0.2
Requires-Dist: xlrd>=2.0.1
Requires-Dist: openpyxl>=3.1.5
Provides-Extra: dev
Requires-Dist: pytest>=8.3.4; extra == "dev"
Requires-Dist: pytest-cov>=6.0.0; extra == "dev"
Requires-Dist: flake8>=7.1.2; extra == "dev"
Requires-Dist: sphinx>=8.2.1; extra == "dev"
Dynamic: license-file
